cloud_pak_operations_cli-0.11.0.dist-info/licenses/LICENSE
cpo/__init__.py
cpo/cpo.py
cpo/commands/__init__.py
cpo/commands/adm/__init__.py
cpo/commands/adm/download_dependencies.py
cpo/commands/adm/get_shell_completion_script_location.py
cpo/commands/adm/update_dev.py
cpo/commands/adm/config/__init__.py
cpo/commands/adm/config/set_bool.py
cpo/commands/adm/config/unset.py
cpo/commands/adm/credentials/__init__.py
cpo/commands/adm/credentials/rm.py
cpo/commands/adm/credentials/store.py
cpo/commands/adm/ibm_internal_plugin/__init__.py
cpo/commands/adm/ibm_internal_plugin/install.py
cpo/commands/adm/ibm_internal_plugin/ls.py
cpo/commands/adm/ibm_internal_plugin/store_artifactory_credentials.py
cpo/commands/adm/ibm_internal_plugin/upgrade_plugins.py
cpo/commands/cluster/__init__.py
cpo/commands/cluster/add.py
cpo/commands/cluster/current.py
cpo/commands/cluster/edit.py
cpo/commands/cluster/get_cluster_access_token.py
cpo/commands/cluster/ls.py
cpo/commands/cluster/oc_login.py
cpo/commands/cluster/reset_current_cluster.py
cpo/commands/cluster/rm.py
cpo/commands/cluster/use.py
cpo/commands/cluster/operator/__init__.py
cpo/commands/cluster/operator/install_cert_manager.py
cpo/commands/cluster/operator/install_node_feature_discovery_operator.py
cpo/commands/cluster/operator/install_nvidia_gpu_operator.py
cpo/commands/cluster/operator/install_red_hat_openshift_ai_operator.py
cpo/commands/cluster/pods/__init__.py
cpo/commands/cluster/pods/delete_terminated_pods.py
cpo/commands/cluster/pull_secret/__init__.py
cpo/commands/cluster/pull_secret/ls.py
cpo/commands/cluster/pull_secret/print.py
cpo/commands/cluster/pull_secret/rm.py
cpo/commands/cluster/pull_secret/set.py
cpo/commands/cluster/storage/__init__.py
cpo/commands/cluster/storage/install_kubernetes_nfs_subdir_external_provisioner.py
cpo/commands/cluster/storage/install_openshift_data_foundation.py
cpo/commands/ibmcloud/__init__.py
cpo/commands/ibmcloud/create_iam_token.py
cpo/commands/ibmcloud/login.py
cpo/commands/ibmcloud/logout.py
cpo/commands/ibmcloud/regenerate_api_key.py
cloud_pak_operations_cli-0.11.0.dist-info/METADATA
cloud_pak_operations_cli-0.11.0.dist-info/WHEEL
cloud_pak_operations_cli-0.11.0.dist-info/entry_points.txt
cloud_pak_operations_cli-0.11.0.dist-info/top_level.txt
cloud_pak_operations_cli-0.11.0.dist-info/RECORD
