Metadata-Version: 2.4
Name: cloud-pak-operations-cli
Version: 0.11.0
Summary: IBM Cloud Pak Operations CLI
Author-email: IBM Corporation <db2datagate@ibm.com>
Project-URL: repository, https://github.com/IBM/cloud-pak-operations-cli
Classifier: Development Status :: 4 - Beta
Classifier: License :: OSI Approved :: Apache Software License
Classifier: Operating System :: MacOS
Classifier: Operating System :: Microsoft :: Windows
Classifier: Operating System :: POSIX :: Linux
Classifier: Programming Language :: Python :: 3.12
Requires-Python: >=3.12
License-File: LICENSE
Requires-Dist: ansible_runner
Requires-Dist: ansible>=12
Requires-Dist: asyncssh
Requires-Dist: click-option-group
Requires-Dist: click
Requires-Dist: colorama
Requires-Dist: filelock
Requires-Dist: halo
Requires-Dist: ibm_cloud_sdk_core
Requires-Dist: ifaddr
Requires-Dist: jmespath
Requires-Dist: jsonschema
Requires-Dist: kubernetes>=12
Requires-Dist: pydantic
Requires-Dist: pypi_simple
Requires-Dist: pytest
Requires-Dist: pyyaml
Requires-Dist: q
Requires-Dist: requests
Requires-Dist: semver
Requires-Dist: sortedcontainers
Requires-Dist: tabulate
Requires-Dist: tqdm
Requires-Dist: urllib3
Dynamic: license-file
